mdmpyclient/__init__.py
mdmpyclient/mdm.py
MDMPyClient-1.0.2.dist-info/LICENSE
MDMPyClient-1.0.2.dist-info/METADATA
MDMPyClient-1.0.2.dist-info/WHEEL
MDMPyClient-1.0.2.dist-info/top_level.txt
MDMPyClient-1.0.2.dist-info/RECORD
